asana_preview/__init__.py
asana_preview/api_client.py
asana_preview/configuration.py
asana_preview/rest.py
asana_preview/api/__init__.py
asana_preview/models/__init__.py
asana_preview/models/add_custom_field_setting_request.py
asana_preview/models/add_followers_request.py
asana_preview/models/add_members_request.py
asana_preview/models/asana_named_resource.py
asana_preview/models/asana_resource.py
asana_preview/models/attachment_base.py
asana_preview/models/attachment_compact.py
asana_preview/models/attachment_request.py
asana_preview/models/attachment_response.py
asana_preview/models/attachment_response_parent.py
asana_preview/models/audit_log_event.py
asana_preview/models/audit_log_event_actor.py
asana_preview/models/audit_log_event_context.py
asana_preview/models/audit_log_event_details.py
asana_preview/models/audit_log_event_resource.py
asana_preview/models/batch_request.py
asana_preview/models/batch_request_action.py
asana_preview/models/batch_request_action_options.py
asana_preview/models/batch_request_actions.py
asana_preview/models/batch_request_options.py
narwhalyeti/__init__.py
narwhalyeti/api_client.py
narwhalyeti/configuration.py
narwhalyeti/rest.py
narwhalyeti/api/__init__.py
narwhalyeti/api/attachments_api.py
narwhalyeti/api/audit_log_api_api.py
narwhalyeti/api/batch_api_api.py
narwhalyeti/api/custom_field_settings_api.py
narwhalyeti/api/custom_fields_api.py
narwhalyeti/api/events_api.py
narwhalyeti/api/goal_relationships_api.py
narwhalyeti/api/goals_api.py
narwhalyeti/api/jobs_api.py
narwhalyeti/api/memberships_api.py
narwhalyeti/api/organization_exports_api.py
narwhalyeti/api/portfolio_memberships_api.py
narwhalyeti/api/portfolios_api.py
narwhalyeti/api/project_briefs_api.py
narwhalyeti/api/project_memberships_api.py
narwhalyeti/api/project_statuses_api.py
narwhalyeti/api/project_templates_api.py
narwhalyeti/api/projects_api.py
narwhalyeti/api/rules_api.py
narwhalyeti/api/sections_api.py
narwhalyeti/api/status_updates_api.py
narwhalyeti-0.0.7.dist-info/METADATA
narwhalyeti-0.0.7.dist-info/WHEEL
narwhalyeti-0.0.7.dist-info/top_level.txt
narwhalyeti-0.0.7.dist-info/RECORD
