Metadata-Version: 2.1
Name: narwhalyeti
Version: 0.0.7
Summary: Asana
Home-page: 
Author-email: 
Keywords: Swagger,Asana
Requires-Dist: urllib3 (>=1.15)
Requires-Dist: six (>=1.10)
Requires-Dist: certifi
Requires-Dist: python-dateutil
